alibabacloud_ft20150303/__init__.py
alibabacloud_ft20150303/client.py
alibabacloud_ft20150303/models.py
alibabacloud_ft20150303_py2-1.0.0.dist-info/LICENSE
alibabacloud_ft20150303_py2-1.0.0.dist-info/METADATA
alibabacloud_ft20150303_py2-1.0.0.dist-info/WHEEL
alibabacloud_ft20150303_py2-1.0.0.dist-info/top_level.txt
alibabacloud_ft20150303_py2-1.0.0.dist-info/RECORD
